Spruce_datetime-0.2.2-py2.7-nspkg.pth
spruce/datetime/_tz.py
spruce/datetime/_conversion.py
spruce/datetime/__init__.py
spruce/datetime/_str.py
spruce/datetime/_misc.py
Spruce_datetime-0.2.2.dist-info/METADATA
Spruce_datetime-0.2.2.dist-info/entry_points.txt
Spruce_datetime-0.2.2.dist-info/RECORD
Spruce_datetime-0.2.2.dist-info/top_level.txt
Spruce_datetime-0.2.2.dist-info/namespace_packages.txt
Spruce_datetime-0.2.2.dist-info/WHEEL
Spruce_datetime-0.2.2.dist-info/metadata.json
Spruce_datetime-0.2.2.dist-info/DESCRIPTION.rst
