Metadata-Version: 2.0
Name: Spruce-datetime
Version: 0.2.2
Summary: Dates and times
Home-page: UNKNOWN
Author: Ivan D Vasin
Author-email: nisavid@gmail.com
License: GNU LESSER GENERAL PUBLIC LICENSE
Requires-Dist: pytz
